Metadata-Version: 2.1
Name: apt-mirror-python
Version: 0.4.6
Summary: A small and efficient tool that lets you mirror a part of or the whole Debian GNU/Linux distribution or any other apt sources.
Home-page: https://github.com/sir-xw/apt-mirror-python
Author: Xie Wei
Author-email: xw.master@live.cn
License: UNKNOWN
Platform: UNKNOWN
Classifier: Programming Language :: Python
Classifier: License :: OSI Approved :: GNU General Public License v2 (GPLv2)
Classifier: Operating System :: POSIX :: Linux
